dhelp/__init__.py
dhelp/settings.py
dhelp/web.py
dhelp/files/__init__.py
dhelp/files/_bases.py
dhelp/files/csv.py
dhelp/files/txt.py
dhelp/files/tests/__init__.py
dhelp/files/tests/test_bases.py
dhelp/files/tests/test_csv.py
dhelp/files/tests/test_txt.py
dhelp/tests/__init__.py
dhelp/tests/test_settings.py
dhelp/tests/test_web_page.py
dhelp/text/__init__.py
dhelp/text/_bases.py
dhelp/text/cltk.py
dhelp/text/nltk.py
dhelp/text/tests/__init__.py
dhelp/text/tests/test_ancient_greek.py
dhelp/text/tests/test_english.py
dhelp/text/tests/test_latin.py
dhelp-0.0.5.dist-info/DESCRIPTION.rst
dhelp-0.0.5.dist-info/LICENSE.txt
dhelp-0.0.5.dist-info/METADATA
dhelp-0.0.5.dist-info/RECORD
dhelp-0.0.5.dist-info/WHEEL
dhelp-0.0.5.dist-info/metadata.json
dhelp-0.0.5.dist-info/top_level.txt
