Metadata-Version: 2.0
Name: dhelp
Version: 0.0.5
Summary: DH Python tools for scraping web pages, pre-processing
Home-page: https://github.com/thePortus/dhelp
Author: David J. Thomas
Author-email: dave.a.base@gmail.com
License: UNKNOWN
Download-URL: https://github.com/thePortus/dhelp/archive/master.zip
Keywords: digital-humanities,digital-history,digital-analysis,text-processing,text-analysis,nltk,nlp,natural-language-processing,greek,latin
Platform: UNKNOWN
Classifier: Programming Language :: Python
Classifier: Programming Language :: Python :: 3
Classifier: Programming Language :: Python :: 3.6
Classifier: Development Status :: 3 - Alpha
Classifier: License :: OSI Approved :: MIT License
Classifier: Operating System :: MacOS :: MacOS X
Classifier: Operating System :: POSIX :: Linux
Classifier: Topic :: Sociology :: History
Classifier: Topic :: Text Processing
Classifier: Topic :: Text Processing :: General
Classifier: Topic :: Text Processing :: Linguistic
Classifier: Intended Audience :: Education
Classifier: Intended Audience :: Science/Research
Classifier: Natural Language :: English
Classifier: Natural Language :: Latin
Classifier: Natural Language :: Greek
Requires-Dist: beautifulsoup4 (==4.6.0)
Requires-Dist: certifi (==2018.1.18)
Requires-Dist: chardet (==3.0.4)
Requires-Dist: idna (==2.6)
Requires-Dist: nltk (==3.2.5)
Requires-Dist: requests (==2.18.4)
Requires-Dist: six (==1.11.0)
Requires-Dist: urllib3 (==1.22)
